{"worker_id": "1562", "duration": 244.6704285144806, "data": {"character": "a round man with a bushy mustache", "persona": "I am a man who is obese. I enjoy eating the finest desserts. I hope to never have a heart attack.", "description": "You are in the Port Tavern.\nThe port tavern is the shadiest of all the shady bars in the city. Every night, on its grimy stools at the wooden bar, you can find some of the slimiest sailors in the world. The walls are of peeling blue paint and are always dripping with condensation. Women of ill-repute line one wall, old men on the verge of passing out line another. The floor is littered with trash, barnacles, and bodily fluids. Tending the bar is a small, round man with a bushy mustache.\nThere's some bodily fluids, a mug of mead, some grimy stools, and a wooden bar here.\n\nYou are carrying a dessert, and wearing a belt.", "goal": "put belt on grimy stools", "graph": "{\n    \"agents\": [\n        \"round man with a bushy mustache_10\"\n    ],\n    \"nodes\": {\n        \"barnacles_4\": {\n            \"agent\": false,\n            \"classes\": [\n                \"object\"\n            ],\n            \"contain_size\": 0,\n            \"contained_nodes\": {},\n            \"container\": false,\n            \"container_node\": {\n                \"target_id\": \"grimy stools_3\"\n            },\n            \"db_id\": 5547,\n            \"dead\": false,\n            \"desc\": \"This barnacle is rough to the touch and smells slightly of seawater.\",\n            \"drink\": false,\n            \"equipped\": null,\n            \"food\": false,\n            \"food_energy\": 0,\n            \"gettable\": true,\n            \"locked_edge\": null,\n            \"name\": \"barnacles\",\n            \"name_prefix\": \"some\",\n            \"names\": [\n                \"barnacles\"\n            ],\n            \"node_id\": \"barnacles_4\",\n            \"object\": true,\n            \"room\": false,\n            \"size\": 1,\n            \"stats\": {\n                \"damage\": 0,\n                \"defense\": 0\n            },\n            \"surface_type\": \"on\",\n            \"value\": 1,\n            \"wearable\": false,\n            \"wieldable\": false\n        },\n        \"belt_14\": {\n            \"agent\": false,\n            \"classes\": [\n                \"object\",\n                \"wearable\"\n            ],\n            \"contain_size\": 0,\n            \"contained_nodes\": {},\n            \"container\": false,\n            \"container_node\": {\n                \"target_id\": \"round man with a bushy mustache_10\"\n            },\n            \"db_id\": 9129,\n            \"dead\": false,\n            \"desc\": \"The belt looks as though it has seen better days.\",\n            \"drink\": false,\n            \"equipped\": true,\n            \"food\": false,\n            \"food_energy\": 0,\n            \"gettable\": true,\n            \"locked_edge\": null,\n            \"name\": \"belt\",\n            \"name_prefix\": \"a\",\n            \"names\": [\n                \"belt\"\n            ],\n            \"node_id\": \"belt_14\",\n            \"object\": true,\n            \"room\": false,\n            \"size\": 1,\n            \"stats\": {\n                \"attack\": 1\n            },\n            \"surface_type\": \"on\",\n            \"value\": 1,\n            \"wearable\": true,\n            \"wieldable\": false\n        },\n        \"bodily fluids_9\": {\n            \"agent\": false,\n            \"classes\": [\n                \"drink\",\n                \"not_gettable\",\n                \"object\"\n            ],\n            \"contain_size\": 0,\n            \"contained_nodes\": {},\n            \"container\": false,\n            \"container_node\": {\n                \"target_id\": \"port tavern_0\"\n            },\n            \"db_id\": 6559,\n            \"dead\": false,\n            \"desc\": \"You peer closer at one of them. Bodily fluids created a viscous sheen on the floor where the incident occurred.\",\n            \"drink\": true,\n            \"equipped\": null,\n            \"food\": false,\n            \"food_energy\": 0,\n            \"gettable\": true,\n            \"locked_edge\": null,\n            \"name\": \"bodily fluids\",\n            \"name_prefix\": \"some\",\n            \"names\": [\n                \"bodily fluids\"\n            ],\n            \"node_id\": \"bodily fluids_9\",\n            \"object\": true,\n            \"room\": false,\n            \"size\": 1,\n            \"stats\": {\n                \"damage\": 0,\n                \"defense\": 0\n            },\n            \"surface_type\": \"on\",\n            \"value\": 1,\n            \"wearable\": false,\n            \"wieldable\": false\n        },\n        \"crow bar_7\": {\n            \"agent\": false,\n            \"classes\": [\n                \"object\",\n                \"wieldable\"\n            ],\n            \"contain_size\": 0,\n            \"contained_nodes\": {},\n            \"container\": false,\n            \"container_node\": {\n                \"target_id\": \"wooden bar_6\"\n            },\n            \"db_id\": 7211,\n            \"dead\": false,\n            \"desc\": \"The crow bar is shiny and beutiful, it is made out of a weird metal alloy.\",\n            \"drink\": false,\n            \"equipped\": null,\n            \"food\": false,\n            \"food_energy\": 0,\n            \"gettable\": true,\n            \"locked_edge\": null,\n            \"name\": \"crow bar\",\n            \"name_prefix\": \"a\",\n            \"names\": [\n                \"crow bar\"\n            ],\n            \"node_id\": \"crow bar_7\",\n            \"object\": true,\n            \"room\": false,\n            \"size\": 1,\n            \"stats\": {\n                \"attack\": 1\n            },\n            \"surface_type\": \"on\",\n            \"value\": 1,\n            \"wearable\": false,\n            \"wieldable\": true\n        },\n        \"dessert_11\": {\n            \"agent\": false,\n            \"classes\": [\n                \"container\",\n                \"food\",\n                \"object\"\n            ],\n            \"contain_size\": 1,\n            \"contained_nodes\": {\n                \"large club_13\": {\n                    \"target_id\": \"large club_13\"\n                },\n                \"large ladle_12\": {\n                    \"target_id\": \"large ladle_12\"\n                }\n            },\n            \"container\": true,\n            \"container_node\": {\n                \"target_id\": \"round man with a bushy mustache_10\"\n            },\n            \"db_id\": 9279,\n            \"dead\": false,\n            \"desc\": \"Dessert for the feast was a pastry made of honey, barley and spices.\",\n            \"drink\": false,\n            \"equipped\": null,\n            \"food\": true,\n            \"food_energy\": 0,\n            \"gettable\": true,\n            \"locked_edge\": null,\n            \"name\": \"dessert\",\n            \"name_prefix\": \"a\",\n            \"names\": [\n                \"dessert\"\n            ],\n            \"node_id\": \"dessert_11\",\n            \"object\": true,\n            \"room\": false,\n            \"size\": 1,\n            \"stats\": {\n                \"damage\": 0,\n                \"defense\": 0\n            },\n            \"surface_type\": \"on\",\n            \"value\": 1,\n            \"wearable\": false,\n            \"wieldable\": false\n        },\n        \"grimy stools at the wooden bar_8\": {\n            \"agent\": false,\n            \"classes\": [\n                \"container\",\n                \"object\"\n            ],\n            \"contain_size\": 3,\n            \"contained_nodes\": {},\n            \"container\": true,\n            \"container_node\": {\n                \"target_id\": \"wooden bar_6\"\n            },\n            \"db_id\": 8799,\n            \"dead\": false,\n            \"desc\": \"The stool is dirty and grimy.  It is made of wood with a leather seat.\",\n            \"drink\": false,\n            \"equipped\": null,\n            \"food\": false,\n            \"food_energy\": 0,\n            \"gettable\": true,\n            \"locked_edge\": null,\n            \"name\": \"grimy stools at the wooden bar\",\n            \"name_prefix\": \"some\",\n            \"names\": [\n                \"grimy stools at the wooden bar\"\n            ],\n            \"node_id\": \"grimy stools at the wooden bar_8\",\n            \"object\": true,\n            \"room\": false,\n            \"size\": 1,\n            \"stats\": {\n                \"damage\": 0,\n                \"defense\": 0\n            },\n            \"surface_type\": \"on\",\n            \"value\": 1,\n            \"wearable\": false,\n            \"wieldable\": false\n        },\n        \"grimy stools_3\": {\n            \"agent\": false,\n            \"classes\": [\n                \"container\",\n                \"not_gettable\",\n                \"object\"\n            ],\n            \"contain_size\": 1,\n            \"contained_nodes\": {\n                \"barnacles_4\": {\n                    \"target_id\": \"barnacles_4\"\n                },\n                \"product_5\": {\n                    \"target_id\": \"product_5\"\n                }\n            },\n            \"container\": true,\n            \"container_node\": {\n                \"target_id\": \"port tavern_0\"\n            },\n            \"db_id\": 6553,\n            \"dead\": false,\n            \"desc\": \"You peer closer at one of them. This stool is old and dusty and has a broken leg\",\n            \"drink\": false,\n            \"equipped\": null,\n            \"food\": false,\n            \"food_energy\": 0,\n            \"gettable\": true,\n            \"locked_edge\": null,\n            \"name\": \"grimy stools\",\n            \"name_prefix\": \"some\",\n            \"names\": [\n                \"grimy stools\"\n            ],\n            \"node_id\": \"grimy stools_3\",\n            \"object\": true,\n            \"room\": false,\n            \"size\": 1,\n            \"stats\": {\n                \"damage\": 0,\n                \"defense\": 0\n            },\n            \"surface_type\": \"on\",\n            \"value\": 1,\n            \"wearable\": false,\n            \"wieldable\": false\n        },\n        \"large club_13\": {\n            \"agent\": false,\n            \"classes\": [\n                \"object\",\n                \"wieldable\"\n            ],\n            \"contain_size\": 0,\n            \"contained_nodes\": {},\n            \"container\": false,\n            \"container_node\": {\n                \"target_id\": \"dessert_11\"\n            },\n            \"db_id\": 10809,\n            \"dead\": false,\n            \"desc\": \"The large club is rounded and battered.\",\n            \"drink\": false,\n            \"equipped\": null,\n            \"food\": false,\n            \"food_energy\": 0,\n            \"gettable\": true,\n            \"locked_edge\": null,\n            \"name\": \"large club\",\n            \"name_prefix\": \"a\",\n            \"names\": [\n                \"large club\"\n            ],\n            \"node_id\": \"large club_13\",\n            \"object\": true,\n            \"room\": false,\n            \"size\": 1,\n            \"stats\": {\n                \"attack\": 1\n            },\n            \"surface_type\": \"on\",\n            \"value\": 1,\n            \"wearable\": false,\n            \"wieldable\": true\n        },\n        \"large ladle_12\": {\n            \"agent\": false,\n            \"classes\": [\n                \"object\",\n                \"wieldable\"\n            ],\n            \"contain_size\": 0,\n            \"contained_nodes\": {},\n            \"container\": false,\n            \"container_node\": {\n                \"target_id\": \"dessert_11\"\n            },\n            \"db_id\": 8473,\n            \"dead\": false,\n            \"desc\": \"A wooden dipping ladle for water or stew.\",\n            \"drink\": false,\n            \"equipped\": null,\n            \"food\": false,\n            \"food_energy\": 0,\n            \"gettable\": true,\n            \"locked_edge\": null,\n            \"name\": \"large ladle\",\n            \"name_prefix\": \"a\",\n            \"names\": [\n                \"large ladle\"\n            ],\n            \"node_id\": \"large ladle_12\",\n            \"object\": true,\n            \"room\": false,\n            \"size\": 1,\n            \"stats\": {\n                \"attack\": 1\n            },\n            \"surface_type\": \"on\",\n            \"value\": 1,\n            \"wearable\": false,\n            \"wieldable\": true\n        },\n        \"mug of mead_1\": {\n            \"agent\": false,\n            \"classes\": [\n                \"container\",\n                \"object\",\n                \"wieldable\"\n            ],\n            \"contain_size\": 2,\n            \"contained_nodes\": {\n                \"mug_2\": {\n                    \"target_id\": \"mug_2\"\n                }\n            },\n            \"container\": true,\n            \"container_node\": {\n                \"target_id\": \"port tavern_0\"\n            },\n            \"db_id\": 6561,\n            \"dead\": false,\n            \"desc\": \"The mug of meed looks tempting.\",\n            \"drink\": false,\n            \"equipped\": null,\n            \"food\": false,\n            \"food_energy\": 0,\n            \"gettable\": true,\n            \"locked_edge\": null,\n            \"name\": \"mug of mead\",\n            \"name_prefix\": \"a\",\n            \"names\": [\n                \"mug of mead\"\n            ],\n            \"node_id\": \"mug of mead_1\",\n            \"object\": true,\n            \"room\": false,\n            \"size\": 1,\n            \"stats\": {\n                \"attack\": 1\n            },\n            \"surface_type\": \"on\",\n            \"value\": 1,\n            \"wearable\": false,\n            \"wieldable\": true\n        },\n        \"mug_2\": {\n            \"agent\": false,\n            \"classes\": [\n                \"container\",\n                \"object\"\n            ],\n            \"contain_size\": 3,\n            \"contained_nodes\": {},\n            \"container\": true,\n            \"container_node\": {\n                \"target_id\": \"mug of mead_1\"\n            },\n            \"db_id\": 8093,\n            \"dead\": false,\n            \"desc\": \"The mug appears to have been carved by a master woodworker.  It is smooth and perfect.\",\n            \"drink\": false,\n            \"equipped\": null,\n            \"food\": false,\n            \"food_energy\": 0,\n            \"gettable\": true,\n            \"locked_edge\": null,\n            \"name\": \"mug\",\n            \"name_prefix\": \"a\",\n            \"names\": [\n                \"mug\"\n            ],\n            \"node_id\": \"mug_2\",\n            \"object\": true,\n            \"room\": false,\n            \"size\": 1,\n            \"stats\": {\n                \"damage\": 0,\n                \"defense\": 0\n            },\n            \"surface_type\": \"on\",\n            \"value\": 1,\n            \"wearable\": false,\n            \"wieldable\": false\n        },\n        \"port tavern_0\": {\n            \"agent\": false,\n            \"classes\": [\n                \"room\"\n            ],\n            \"contain_size\": 1976,\n            \"contained_nodes\": {\n                \"bodily fluids_9\": {\n                    \"target_id\": \"bodily fluids_9\"\n                },\n                \"grimy stools_3\": {\n                    \"target_id\": \"grimy stools_3\"\n                },\n                \"mug of mead_1\": {\n                    \"target_id\": \"mug of mead_1\"\n                },\n                \"round man with a bushy mustache_10\": {\n                    \"target_id\": \"round man with a bushy mustache_10\"\n                },\n                \"wooden bar_6\": {\n                    \"target_id\": \"wooden bar_6\"\n                }\n            },\n            \"container_node\": {\n                \"target_id\": \"VOID\"\n            },\n            \"db_id\": 104,\n            \"desc\": \"The port tavern is the shadiest of all the shady bars in the city. Every night, on its grimy stools at the wooden bar, you can find some of the slimiest sailors in the world. The walls are of peeling blue paint and are always dripping with condensation. Women of ill-repute line one wall, old men on the verge of passing out line another. The floor is littered with trash, barnacles, and bodily fluids. Tending the bar is a small, round man with a bushy mustache.\",\n            \"extra_desc\": \"The port tavern used to be a private domicile. It belonged to a wealthy merchant who lived there with his beautiful wife and daughters. This merchant was intelligent, charming, well-respected, and was addicted to gambling. Luck had been on his side for his entire life, until one night when he was playing cards against local merchants. Out of cash and overconfident, he bet his house to a small, round man with a bushy mustache and a questionable past.\",\n            \"name\": \"Port Tavern\",\n            \"name_prefix\": \"the\",\n            \"names\": [\n                \"Port Tavern\"\n            ],\n            \"neighbors\": {},\n            \"node_id\": \"port tavern_0\",\n            \"object\": false,\n            \"room\": true,\n            \"size\": 2000,\n            \"surface_type\": \"in\"\n        },\n        \"product_5\": {\n            \"agent\": false,\n            \"classes\": [\n                \"drink\",\n                \"food\",\n                \"object\",\n                \"wieldable\"\n            ],\n            \"contain_size\": 0,\n            \"contained_nodes\": {},\n            \"container\": false,\n            \"container_node\": {\n                \"target_id\": \"grimy stools_3\"\n            },\n            \"db_id\": 7729,\n            \"dead\": false,\n            \"desc\": \"This product is unque and a great peice of art.\",\n            \"drink\": true,\n            \"equipped\": null,\n            \"food\": true,\n            \"food_energy\": 0,\n            \"gettable\": true,\n            \"locked_edge\": null,\n            \"name\": \"product\",\n            \"name_prefix\": \"a\",\n            \"names\": [\n                \"product\"\n            ],\n            \"node_id\": \"product_5\",\n            \"object\": true,\n            \"room\": false,\n            \"size\": 1,\n            \"stats\": {\n                \"attack\": 1\n            },\n            \"surface_type\": \"on\",\n            \"value\": 1,\n            \"wearable\": false,\n            \"wieldable\": true\n        },\n        \"round man with a bushy mustache_10\": {\n            \"agent\": true,\n            \"aggression\": 0,\n            \"char_type\": \"person\",\n            \"classes\": [\n                \"agent\"\n            ],\n            \"contain_size\": 18,\n            \"contained_nodes\": {\n                \"belt_14\": {\n                    \"target_id\": \"belt_14\"\n                },\n                \"dessert_11\": {\n                    \"target_id\": \"dessert_11\"\n                }\n            },\n            \"container_node\": {\n                \"target_id\": \"port tavern_0\"\n            },\n            \"damage\": 1,\n            \"db_id\": 4181,\n            \"defense\": 0,\n            \"desc\": \"This man is fat due to eating desserts.\",\n            \"followed_by\": {},\n            \"following\": null,\n            \"food_energy\": 1,\n            \"health\": 2,\n            \"is_player\": false,\n            \"name\": \"round man with a bushy mustache\",\n            \"name_prefix\": \"a\",\n            \"names\": [\n                \"round man with a bushy mustache\"\n            ],\n            \"node_id\": \"round man with a bushy mustache_10\",\n            \"object\": false,\n            \"persona\": \"I am a man who is obese. I enjoy eating the finest desserts. I hope to never have a heart attack.\",\n            \"room\": false,\n            \"size\": 20,\n            \"speed\": 5\n        },\n        \"wooden bar_6\": {\n            \"agent\": false,\n            \"classes\": [\n                \"container\",\n                \"not_gettable\",\n                \"object\"\n            ],\n            \"contain_size\": 1,\n            \"contained_nodes\": {\n                \"crow bar_7\": {\n                    \"target_id\": \"crow bar_7\"\n                },\n                \"grimy stools at the wooden bar_8\": {\n                    \"target_id\": \"grimy stools at the wooden bar_8\"\n                }\n            },\n            \"container\": true,\n            \"container_node\": {\n                \"target_id\": \"port tavern_0\"\n            },\n            \"db_id\": 6555,\n            \"dead\": false,\n            \"desc\": \"The bar is old, but still has plenty life left in it. passed down through generations, it's surface is adorned in scratches, knife marks, and name carvings that add a sense of beauty and immeasurable value to the aging piece.\",\n            \"drink\": false,\n            \"equipped\": null,\n            \"food\": false,\n            \"food_energy\": 0,\n            \"gettable\": true,\n            \"locked_edge\": null,\n            \"name\": \"wooden bar\",\n            \"name_prefix\": \"a\",\n            \"names\": [\n                \"wooden bar\"\n            ],\n            \"node_id\": \"wooden bar_6\",\n            \"object\": true,\n            \"room\": false,\n            \"size\": 1,\n            \"stats\": {\n                \"damage\": 0,\n                \"defense\": 0\n            },\n            \"surface_type\": \"on\",\n            \"value\": 1,\n            \"wearable\": false,\n            \"wieldable\": false\n        }\n    },\n    \"objects\": [\n        \"barnacles_4\",\n        \"belt_14\",\n        \"bodily fluids_9\",\n        \"crow bar_7\",\n        \"dessert_11\",\n        \"grimy stools at the wooden bar_8\",\n        \"grimy stools_3\",\n        \"large club_13\",\n        \"large ladle_12\",\n        \"mug of mead_1\",\n        \"mug_2\",\n        \"product_5\",\n        \"wooden bar_6\"\n    ],\n    \"rooms\": [\n        \"port tavern_0\"\n    ]\n}", "short_motivation": "I will use the belt to scare the ill-repute women to come to me.", "mid_motivation": "I will have an affair with one of the prettiest of the ill-repute women.", "long_motivation": "I will marry the prettiest ill-repute woman and have pretty children with her.", "timeline": [{"label": "4 hours ago", "action": "go the belt shop"}, {"label": "1 hour ago", "action": "get belt shop from the shop"}, {"label": "10 minutes ago", "action": "go the Port Tavern"}, {"label": "5 minutes from now", "action": "wield the belt"}, {"label": "15 minutes from now", "action": "hit the ill-repute women to scare them."}, {"label": "1 hour from now", "action": "hug the prettiest woman in them."}]}}