{"worker_id": "789", "duration": 256.1676082611084, "data": {"character": "the guard", "persona": "I love to be on the lookout.  I intend to keep everyone safe.  I work hard each time.", "description": "You are in the The tower base.\nThe tower base has a path of cobblestone leading to the entrance. Two torches are lit with large blazing fires. Most of the tower base is covered in moss.\nThere's a tower, a torch, a path, and a moss here.\nThe villager is here.\n\nYou are carrying nothing.", "goal": "follow villager", "graph": "{\n    \"agents\": [\n        \"guard\",\n        \"villager\"\n    ],\n    \"nodes\": {\n        \"guard\": {\n            \"agent\": true,\n            \"aggression\": 0,\n            \"char_type\": \"person\",\n            \"classes\": [\n                \"agent\"\n            ],\n            \"contain_size\": 20,\n            \"contained_nodes\": {},\n            \"container_node\": {\n                \"target_id\": \"the tower base_0\"\n            },\n            \"damage\": 1,\n            \"db_id\": 1392,\n            \"defense\": 0,\n            \"desc\": \"I love to be on the lookout.  I intend to keep everyone safe.  I work hard each time.\",\n            \"followed_by\": {},\n            \"following\": null,\n            \"food_energy\": 1,\n            \"health\": 10,\n            \"is_player\": true,\n            \"name\": \"guard\",\n            \"name_prefix\": \"the\",\n            \"names\": [\n                \"guard\"\n            ],\n            \"node_id\": \"guard\",\n            \"object\": false,\n            \"persona\": \"I love to be on the lookout.  I intend to keep everyone safe.  I work hard each time.\",\n            \"room\": false,\n            \"size\": 20,\n            \"speed\": 5\n        },\n        \"moss_4\": {\n            \"agent\": false,\n            \"classes\": [\n                \"object\"\n            ],\n            \"contain_size\": 0,\n            \"contained_nodes\": {},\n            \"container\": false,\n            \"container_node\": {\n                \"target_id\": \"the tower base_0\"\n            },\n            \"db_id\": null,\n            \"dead\": false,\n            \"desc\": \"The moss is moist and feels soft.\",\n            \"drink\": false,\n            \"equipped\": null,\n            \"food\": false,\n            \"food_energy\": 0,\n            \"gettable\": true,\n            \"locked_edge\": null,\n            \"name\": \"moss\",\n            \"name_prefix\": \"a\",\n            \"names\": [\n                \"moss\"\n            ],\n            \"node_id\": \"moss_4\",\n            \"object\": true,\n            \"room\": false,\n            \"size\": 1,\n            \"stats\": {\n                \"damage\": 0,\n                \"defense\": 0\n            },\n            \"surface_type\": \"on\",\n            \"value\": 1,\n            \"wearable\": false,\n            \"wieldable\": false\n        },\n        \"path_2\": {\n            \"agent\": false,\n            \"classes\": [\n                \"not_gettable\",\n                \"object\"\n            ],\n            \"contain_size\": 0,\n            \"contained_nodes\": {},\n            \"container\": false,\n            \"container_node\": {\n                \"target_id\": \"the tower base_0\"\n            },\n            \"db_id\": null,\n            \"dead\": false,\n            \"desc\": \"A path trodden through by some.\",\n            \"drink\": false,\n            \"equipped\": null,\n            \"food\": false,\n            \"food_energy\": 0,\n            \"gettable\": true,\n            \"locked_edge\": null,\n            \"name\": \"path\",\n            \"name_prefix\": \"a\",\n            \"names\": [\n                \"path\"\n            ],\n            \"node_id\": \"path_2\",\n            \"object\": true,\n            \"room\": false,\n            \"size\": 1,\n            \"stats\": {\n                \"damage\": 0,\n                \"defense\": 0\n            },\n            \"surface_type\": \"on\",\n            \"value\": 1,\n            \"wearable\": false,\n            \"wieldable\": false\n        },\n        \"the tower base_0\": {\n            \"agent\": false,\n            \"classes\": [\n                \"room\"\n            ],\n            \"contain_size\": 1956,\n            \"contained_nodes\": {\n                \"guard\": {\n                    \"target_id\": \"guard\"\n                },\n                \"moss_4\": {\n                    \"target_id\": \"moss_4\"\n                },\n                \"path_2\": {\n                    \"target_id\": \"path_2\"\n                },\n                \"torch_3\": {\n                    \"target_id\": \"torch_3\"\n                },\n                \"tower_1\": {\n                    \"target_id\": \"tower_1\"\n                },\n                \"villager\": {\n                    \"target_id\": \"villager\"\n                }\n            },\n            \"container_node\": {\n                \"target_id\": \"VOID\"\n            },\n            \"db_id\": 322,\n            \"desc\": \"The tower base has a path of cobblestone leading to the entrance. Two torches are lit with large blazing fires. Most of the tower base is covered in moss.\",\n            \"extra_desc\": \"This tower is a beacon of hope for the nearby village. It is where soldiers gather in times of war. The path to the tower has been walked upon by the country's greatest generals.\",\n            \"name\": \"The tower base\",\n            \"name_prefix\": \"the\",\n            \"names\": [\n                \"The tower base\"\n            ],\n            \"neighbors\": {},\n            \"node_id\": \"the tower base_0\",\n            \"object\": false,\n            \"room\": true,\n            \"size\": 1,\n            \"surface_type\": \"in\"\n        },\n        \"torch_3\": {\n            \"agent\": false,\n            \"classes\": [\n                \"not_gettable\",\n                \"object\"\n            ],\n            \"contain_size\": 0,\n            \"contained_nodes\": {},\n            \"container\": false,\n            \"container_node\": {\n                \"target_id\": \"the tower base_0\"\n            },\n            \"db_id\": null,\n            \"dead\": false,\n            \"desc\": \"The torch glows bright and warm.  The handle of the torch is made of bamboo.\",\n            \"drink\": false,\n            \"equipped\": null,\n            \"food\": false,\n            \"food_energy\": 0,\n            \"gettable\": true,\n            \"locked_edge\": null,\n            \"name\": \"torch\",\n            \"name_prefix\": \"a\",\n            \"names\": [\n                \"torch\"\n            ],\n            \"node_id\": \"torch_3\",\n            \"object\": true,\n            \"room\": false,\n            \"size\": 1,\n            \"stats\": {\n                \"damage\": 0,\n                \"defense\": 0\n            },\n            \"surface_type\": \"on\",\n            \"value\": 1,\n            \"wearable\": false,\n            \"wieldable\": false\n        },\n        \"tower_1\": {\n            \"agent\": false,\n            \"classes\": [\n                \"not_gettable\",\n                \"object\"\n            ],\n            \"contain_size\": 0,\n            \"contained_nodes\": {},\n            \"container\": false,\n            \"container_node\": {\n                \"target_id\": \"the tower base_0\"\n            },\n            \"db_id\": null,\n            \"dead\": false,\n            \"desc\": \"The tower reaches high into the sky and provides a view far into the distance. It's stone walls are sturdy and immovable.\",\n            \"drink\": false,\n            \"equipped\": null,\n            \"food\": false,\n            \"food_energy\": 0,\n            \"gettable\": true,\n            \"locked_edge\": null,\n            \"name\": \"tower\",\n            \"name_prefix\": \"a\",\n            \"names\": [\n                \"tower\"\n            ],\n            \"node_id\": \"tower_1\",\n            \"object\": true,\n            \"room\": false,\n            \"size\": 1,\n            \"stats\": {\n                \"damage\": 0,\n                \"defense\": 0\n            },\n            \"surface_type\": \"on\",\n            \"value\": 1,\n            \"wearable\": false,\n            \"wieldable\": false\n        },\n        \"villager\": {\n            \"agent\": true,\n            \"aggression\": 0,\n            \"char_type\": \"person\",\n            \"classes\": [\n                \"agent\"\n            ],\n            \"contain_size\": 20,\n            \"contained_nodes\": {},\n            \"container_node\": {\n                \"target_id\": \"the tower base_0\"\n            },\n            \"damage\": 1,\n            \"db_id\": 3140,\n            \"defense\": 0,\n            \"desc\": \"I've been walking for days. The sun is bright and hot while the nights are dark and cold. Our young is getting sick while our old are getting weary of finding a safe place to arrive to. We have heard rumors that there is a camp one day north. I can only pray we hold on for that long.\",\n            \"followed_by\": {},\n            \"following\": null,\n            \"food_energy\": 1,\n            \"health\": 10,\n            \"is_player\": true,\n            \"name\": \"villager\",\n            \"name_prefix\": \"the\",\n            \"names\": [\n                \"villager\"\n            ],\n            \"node_id\": \"villager\",\n            \"object\": false,\n            \"persona\": \"I've been walking for days. The sun is bright and hot while the nights are dark and cold. Our young is getting sick while our old are getting weary of finding a safe place to arrive to. We have heard rumors that there is a camp one day north. I can only pray we hold on for that long.\",\n            \"room\": false,\n            \"size\": 20,\n            \"speed\": 5\n        }\n    },\n    \"objects\": [\n        \"moss_4\",\n        \"path_2\",\n        \"torch_3\",\n        \"tower_1\"\n    ],\n    \"rooms\": [\n        \"the tower base_0\"\n    ]\n}", "short_motivation": "I want to look out for shady individuals and ensure they're following the law", "mid_motivation": "I want to arrest and detain any unlawful individuals in the village", "long_motivation": "I want to keep the town free of lawlessness and keep order. ", "timeline": [{"label": "8 hours ago", "action": "eat Food to prepare for a day of work"}, {"label": "1 hour ago", "action": "go the base of the tower to start patrol"}, {"label": "10 minutes ago", "action": "go location of shady villager I spotted"}, {"label": "5 minutes from now", "action": "put my hands in villager's shoulders"}, {"label": "10 minutes from now", "action": "hit Villager"}, {"label": "15 minutes from now", "action": "go to jailhouse with unconscious villager"}]}}